kubernetesclustermonitor/__init__.py
kubernetesclustermonitor/test.py
kubernetesclustermonitor-0.1.0.dist-info/WHEEL
kubernetesclustermonitor-0.1.0.dist-info/METADATA
kubernetesclustermonitor-0.1.0.dist-info/RECORD
